pypenelopetools/__init__.py
pypenelopetools/_version.py
pypenelopetools/material.py
pypenelopetools/test_material.py
pypenelopetools/pencyl/__init__.py
pypenelopetools/pencyl/input.py
pypenelopetools/pencyl/keywords.py
pypenelopetools/pencyl/results.py
pypenelopetools/pencyl/separators.py
pypenelopetools/pencyl/test_input.py
pypenelopetools/penelope/__init__.py
pypenelopetools/penelope/base.py
pypenelopetools/penelope/enums.py
pypenelopetools/penelope/input.py
pypenelopetools/penelope/keyword.py
pypenelopetools/penelope/keywords.py
pypenelopetools/penelope/result.py
pypenelopetools/penelope/separator.py
pypenelopetools/penelope/separators.py
pypenelopetools/penepma/__init__.py
pypenelopetools/penepma/input.py
pypenelopetools/penepma/keywords.py
pypenelopetools/penepma/results.py
pypenelopetools/penepma/separators.py
pypenelopetools/penepma/test_input.py
pypenelopetools/penepma/test_results.py
pypenelopetools/penepma/test_utils.py
pypenelopetools/penepma/utils.py
pypenelopetools/pengeom/__init__.py
pypenelopetools/pengeom/base.py
pypenelopetools/pengeom/geometry.py
pypenelopetools/pengeom/mixin.py
pypenelopetools/pengeom/module.py
pypenelopetools/pengeom/surface.py
pypenelopetools/pengeom/test_geometry.py
pypenelopetools/pengeom/test_module.py
pypenelopetools/pengeom/test_surface.py
pypenelopetools/pengeom/test_transformation.py
pypenelopetools/pengeom/transformation.py
pypenelopetools/penmain/__init__.py
pypenelopetools/penmain/input.py
pypenelopetools/penmain/keywords.py
pypenelopetools/penmain/separators.py
pypenelopetools/penmain/test_input.py
pyPENELOPEtools-1.2.0.dist-info/LICENSE
pyPENELOPEtools-1.2.0.dist-info/METADATA
pyPENELOPEtools-1.2.0.dist-info/WHEEL
pyPENELOPEtools-1.2.0.dist-info/top_level.txt
pyPENELOPEtools-1.2.0.dist-info/RECORD
