Metadata-Version: 2.1
Name: pyPENELOPEtools
Version: 1.2.0
Summary: Python interface to facilitate the use of the Monte Carlo code PENELOPE and its main programs
Home-page: https://github.com/pymontecarlo/pypenelopetools
Author: Philippe T. Pinard
Author-email: philippe.pinard@gmail.com
License: Apache License, Version 2.0
Platform: UNKNOWN
Classifier: Development Status :: 4 - Beta
Classifier: License :: OSI Approved :: Apache Software License
Classifier: Natural Language :: English
Classifier: Programming Language :: Python :: 3 :: Only
Classifier: Operating System :: OS Independent
Classifier: Topic :: Scientific/Engineering
Classifier: Topic :: Scientific/Engineering :: Physics
License-File: LICENSE
Requires-Dist: numpy
Requires-Dist: pyxray
Requires-Dist: setuptools
Requires-Dist: uncertainties
